LICENSE
MANIFEST.in
README.rst
setup.cfg
setup.py
alexlukash_django_shopping_cart.egg-info/PKG-INFO
alexlukash_django_shopping_cart.egg-info/SOURCES.txt
alexlukash_django_shopping_cart.egg-info/dependency_links.txt
alexlukash_django_shopping_cart.egg-info/top_level.txt
cart/__init__.py
cart/admin.py
cart/apps.py
cart/cart.py
cart/context_processor.py
cart/models.py
cart/tests.py
cart/urls.py
cart/views.py
cart/migrations/__init__.py
cart/templatetags/__init__.py
cart/templatetags/cart_tag.py